datclass/__init__.py
datclass/__main__.py
datclass/__version__.py
datclass/utils.py
datclass-0.2.28.dist-info/LICENSE
datclass-0.2.28.dist-info/METADATA
datclass-0.2.28.dist-info/WHEEL
datclass-0.2.28.dist-info/entry_points.txt
datclass-0.2.28.dist-info/top_level.txt
datclass-0.2.28.dist-info/RECORD
