Metadata-Version: 2.1
Name: datclass
Version: 0.2.28
Summary: python package dataclass utils
Author: foyoux
Project-URL: Source, https://github.com/foyoux/datclass
Project-URL: Homepage, https://github.com/foyoux/datclass
Project-URL: Bug Tracker, https://github.com/foyoux/datclass/issues
Keywords: dataclass,dataclasses,utils,nested,extra,attrs,json
Classifier: Programming Language :: Python
Classifier: Programming Language :: Python :: 3
Classifier: Programming Language :: Python :: 3.7
Classifier: Programming Language :: Python :: 3.8
Classifier: Programming Language :: Python :: 3.9
Classifier: Programming Language :: Python :: 3.10
Classifier: Programming Language :: Python :: 3.11
Classifier: Programming Language :: Python :: 3.12
Requires-Python: >=3.7
License-File: LICENSE
Requires-Dist: typing-extensions; python_version < "3.8"
